llama2terminal/__init__.py
llama2terminal/__main__.py
llama2terminal/base/__init__.py
llama2terminal/base/agents.py
llama2terminal/base/config.yaml
llama2terminal/base/prompts.py
llama2terminal/base/test.py
llama2terminal/config/__init__.py
llama2terminal/config/settings.py
llama2terminal/packages/__init__.py
llama2terminal/packages/load.py
llama2terminal/packages/pkg.yaml
llama2terminal/packages/talk/__init__.py
llama2terminal/packages/talk/launch.py
llama2terminal/packages/talk/run.py
llama2terminal/packages/test.py
llama2terminal/wrapper/__init__.py
llama2terminal/wrapper/colors.py
llama2terminal/wrapper/config.py
llama2terminal/wrapper/history.py
llama2terminal/wrapper/IOUtils.py
llama2terminal/wrapper/params.yaml
llama2terminal/wrapper/terminal.py
llama2terminal/wrapper/test.py
llama2terminal/wrapper/utils.py
llama2_terminal-0.1.6.dist-info/entry_points.txt
llama2_terminal-0.1.6.dist-info/LICENSE
llama2_terminal-0.1.6.dist-info/METADATA
llama2_terminal-0.1.6.dist-info/WHEEL
llama2_terminal-0.1.6.dist-info/RECORD
