Metadata-Version: 2.1
Name: llama2-terminal
Version: 0.1.6
Summary: Llama2 Terminal Tools Project
License: MIT
Author: SamthinkGit
Author-email: sebastianmayorquin@gmail.com
Requires-Python: >=3.8,<4.0
Classifier: License :: OSI Approved :: MIT License
Classifier: Programming Language :: Python :: 3
Classifier: Programming Language :: Python :: 3.8
Classifier: Programming Language :: Python :: 3.9
Classifier: Programming Language :: Python :: 3.10
Classifier: Programming Language :: Python :: 3.11
Requires-Dist: bitsandbytes (>=0.39.0)
Requires-Dist: cmd2
Requires-Dist: farm-haystack
Requires-Dist: inquirer
Requires-Dist: pyyaml
Requires-Dist: torch
Requires-Dist: transformers (>=4.0.0)
Requires-Dist: yaspin
